orsay/__init__.py
orsay/boot_django.py
orsay/constants.py
orsay/gallery.py
orsay/orsay.py
orsay/pages.py
orsay/utils.py
django_orsay-0.3.0.dist-info/LICENSE
django_orsay-0.3.0.dist-info/METADATA
django_orsay-0.3.0.dist-info/WHEEL
django_orsay-0.3.0.dist-info/top_level.txt
django_orsay-0.3.0.dist-info/RECORD
