Metadata-Version: 2.1
Name: django-orsay
Version: 0.3.0
Summary: Static site build tools for photo sites
Home-page: https://github.com/cltrudeau/django-orsay
Author: Christopher Trudeau
Author-email: ctrudeau+pypi@arsensa.com
License: MIT
Keywords: django,static site,photo
Classifier: Development Status :: 3 - Alpha
Classifier: Environment :: Web Environment
Classifier: Intended Audience :: Developers
Classifier: License :: OSI Approved :: MIT License
Classifier: Operating System :: OS Independent
Classifier: Programming Language :: Python :: 3.11
Classifier: Topic :: Software Development :: Libraries :: Python Modules
License-File: LICENSE
Requires-Dist: Django (>=4.1)
Requires-Dist: screwdriver (>=0.14.0)
Requires-Dist: Pillow (==9.4.0)
